.gitignore
AUTHORS.rst
CHANGELOG.rst
LICENSE.rst
MANIFEST.in
README.rst
bitbucket-pipelines.yml
nose2.cfg
pyproject.toml
setup.py
tox.ini
dinopy/__init__.pxd
dinopy/__init__.py
dinopy/auxiliary.pxd
dinopy/auxiliary.pyx
dinopy/conversion.pxd
dinopy/conversion.pyx
dinopy/creader.pxd
dinopy/creader.pyx
dinopy/definitions.pxd
dinopy/definitions.pyx
dinopy/exceptions.py
dinopy/fai_io.py
dinopy/fasta_reader.pxd
dinopy/fasta_reader.pyx
dinopy/fasta_writer.pxd
dinopy/fasta_writer.pyx
dinopy/fastq_reader.pxd
dinopy/fastq_reader.pyx
dinopy/fastq_writer.pxd
dinopy/fastq_writer.pyx
dinopy/input_opener.pxd
dinopy/input_opener.pyx
dinopy/nameline_parser.pxd
dinopy/nameline_parser.pyx
dinopy/output_opener.pxd
dinopy/output_opener.pyx
dinopy/processors.pxd
dinopy/processors.pyx
dinopy/sam_reader.pxd
dinopy/sam_reader.pyx
dinopy/sam_writer.pxd
dinopy/sam_writer.pyx
dinopy/sambam.pxd
dinopy/sambam.pyx
dinopy/shape.pxd
dinopy/shape.pyx
dinopy/shaping.pxd
dinopy/shaping.pyx
dinopy/wrap_sais.pxd
dinopy/wrap_sais.pyx
dinopy.egg-info/PKG-INFO
dinopy.egg-info/SOURCES.txt
dinopy.egg-info/dependency_links.txt
dinopy.egg-info/requires.txt
dinopy.egg-info/top_level.txt
dinopy/../README.rst
dinopy/cpp/sais.cpp
docs/Makefile
docs/make.bat
docs/requirements.txt
docs/source/changelog.rst
docs/source/conf.py
docs/source/cython_integration.rst
docs/source/encoding.rst
docs/source/faq.rst
docs/source/hide.css
docs/source/index.rst
docs/source/_static/hide.css
docs/source/autodoc/auxiliary.rst
docs/source/autodoc/conversion.rst
docs/source/autodoc/creader.rst
docs/source/autodoc/definitions.rst
docs/source/autodoc/dinopy.rst
docs/source/autodoc/exceptions.rst
docs/source/autodoc/fai_io.rst
docs/source/autodoc/fasta_reader.rst
docs/source/autodoc/fasta_writer.rst
docs/source/autodoc/fastq_reader.rst
docs/source/autodoc/fastq_writer.rst
docs/source/autodoc/input_opener.rst
docs/source/autodoc/modules.rst
docs/source/autodoc/nameline_parser.rst
docs/source/autodoc/processors.rst
docs/source/autodoc/sam_reader.rst
docs/source/autodoc/sam_writer.rst
docs/source/autodoc/sambam.rst
docs/source/autodoc/shape.rst
docs/source/autodoc/shaping.rst
