Metadata-Version: 2.1
Name: dinopy
Version: 3.0.0
Summary: DNA input and output library for Python and Cython. Includes reader and writer for FASTA and FASTQ files, support for samtools faidx files, and generators for solid and gapped q-grams (k-mers).
Home-page: https://bitbucket.org/HenningTimm/dinopy
Author: Henning Timm, Till Hartmann
Author-email: henning.timm@tu-dortmund.de, till.hartmann@tu-dortmund.de
License: MIT
Classifier: Development Status :: 5 - Production/Stable
Classifier: Intended Audience :: Developers
Classifier: Intended Audience :: Science/Research
Classifier: License :: OSI Approved :: MIT License
Classifier: Natural Language :: English
Classifier: Programming Language :: Python :: 3
Classifier: Programming Language :: Python :: 3.8
Classifier: Programming Language :: Python :: 3.9
Classifier: Programming Language :: Python :: 3.10
Classifier: Programming Language :: Python :: 3.11
Classifier: Programming Language :: Python :: 3.12
Classifier: Programming Language :: Cython
Classifier: Topic :: Scientific/Engineering :: Bio-Informatics
Classifier: Topic :: Scientific/Engineering :: Medical Science Apps.
License-File: LICENSE.rst
License-File: AUTHORS.rst
Requires-Dist: numpy>=1.17
Requires-Dist: Cython>=3.0.0
